gensim_evaluations/methods.py
gensim_evaluations/wikiqueries.py
gensim_evaluations-0.1.2.dist-info/LICENSE.md
gensim_evaluations-0.1.2.dist-info/METADATA
gensim_evaluations-0.1.2.dist-info/WHEEL
gensim_evaluations-0.1.2.dist-info/top_level.txt
gensim_evaluations-0.1.2.dist-info/RECORD
