Metadata-Version: 2.1
Name: gensim-evaluations
Version: 0.1.2
Summary: Methods for evaluating low-resource word embedding models trained with gensim
Home-page: https://github.com/n8stringham/gensim-evaluations
Author: Nate Stringham
Author-email: n8stringham@gmail.com
License: LGPL-2.1
Platform: UNKNOWN
Classifier: License :: OSI Approved :: GNU Lesser General Public License v2 (LGPLv2)
Classifier: Programming Language :: Python :: 3
Requires-Python: >=3.7
Requires-Dist: sparqlwrapper
Requires-Dist: Wikidata
